[
  {
    "blockNumber": 2806440,
    "ID": "1",
    "fromX": 19,
    "fromY": 19,
    "toX": 19,
    "toY": 19,
    "price": "0"
  },
  {
    "blockNumber": 2854895,
    "ID": "2",
    "fromX": 46,
    "fromY": 7,
    "toX": 46,
    "toY": 7,
    "price": "0"
  },
  {
    "blockNumber": 2904436,
    "ID": "3",
    "fromX": 1,
    "fromY": 1,
    "toX": 1,
    "toY": 1,
    "price": "0"
  },
  {
    "blockNumber": 2970228,
    "ID": "4",
    "fromX": 2,
    "fromY": 1,
    "toX": 3,
    "toY": 2,
    "price": "0"
  },
  {
    "blockNumber": 2978969,
    "ID": "5",
    "fromX": 49,
    "fromY": 19,
    "toX": 51,
    "toY": 21,
    "price": "0"
  },
  {
    "blockNumber": 2984083,
    "ID": "6",
    "fromX": 65,
    "fromY": 20,
    "toX": 65,
    "toY": 20,
    "price": "0"
  },
  {
    "blockNumber": 3018548,
    "ID": "7",
    "fromX": 49,
    "fromY": 49,
    "toX": 51,
    "toY": 51,
    "price": "0"
  },
  {
    "blockNumber": 3019226,
    "ID": "8",
    "fromX": 49,
    "fromY": 29,
    "toX": 50,
    "toY": 30,
    "price": "0"
  },
  {
    "blockNumber": 3119720,
    "ID": "9",
    "fromX": 24,
    "fromY": 55,
    "toX": 25,
    "toY": 56,
    "price": "0"
  },
  {
    "blockNumber": 3134672,
    "ID": "10",
    "fromX": 49,
    "fromY": 69,
    "toX": 50,
    "toY": 70,
    "price": "0"
  },
  {
    "blockNumber": 3267989,
    "ID": "11",
    "fromX": 50,
    "fromY": 41,
    "toX": 50,
    "toY": 42,
    "price": "0"
  },
  {
    "blockNumber": 3268010,
    "ID": "12",
    "fromX": 51,
    "fromY": 42,
    "toX": 51,
    "toY": 42,
    "price": "0"
  },
  {
    "blockNumber": 3268660,
    "ID": "13",
    "fromX": 51,
    "fromY": 41,
    "toX": 51,
    "toY": 41,
    "price": "0"
  },
  {
    "blockNumber": 3268690,
    "ID": "14",
    "fromX": 52,
    "fromY": 41,
    "toX": 52,
    "toY": 41,
    "price": "0"
  },
  {
    "blockNumber": 3268691,
    "ID": "15",
    "fromX": 52,
    "fromY": 42,
    "toX": 52,
    "toY": 42,
    "price": "0"
  },
  {
    "blockNumber": 3268697,
    "ID": "16",
    "fromX": 51,
    "fromY": 43,
    "toX": 51,
    "toY": 43,
    "price": "0"
  },
  {
    "blockNumber": 3268698,
    "ID": "17",
    "fromX": 52,
    "fromY": 43,
    "toX": 52,
    "toY": 43,
    "price": "0"
  },
  {
    "blockNumber": 3269284,
    "ID": "18",
    "fromX": 50,
    "fromY": 43,
    "toX": 50,
    "toY": 44,
    "price": "0"
  },
  {
    "blockNumber": 3269289,
    "ID": "19",
    "fromX": 51,
    "fromY": 44,
    "toX": 53,
    "toY": 44,
    "price": "0"
  },
  {
    "blockNumber": 3269302,
    "ID": "20",
    "fromX": 50,
    "fromY": 45,
    "toX": 53,
    "toY": 45,
    "price": "0"
  },
  {
    "blockNumber": 3269304,
    "ID": "21",
    "fromX": 53,
    "fromY": 41,
    "toX": 53,
    "toY": 43,
    "price": "0"
  },
  {
    "blockNumber": 3270816,
    "ID": "22",
    "fromX": 50,
    "fromY": 46,
    "toX": 53,
    "toY": 47,
    "price": "0"
  },
  {
    "blockNumber": 3271089,
    "ID": "23",
    "fromX": 51,
    "fromY": 42,
    "toX": 51,
    "toY": 42,
    "price": "511542000000000000000"
  },
  {
    "blockNumber": 3272016,
    "ID": "24",
    "fromX": 52,
    "fromY": 48,
    "toX": 52,
    "toY": 48,
    "price": "0"
  },
  {
    "blockNumber": 3275509,
    "ID": "25",
    "fromX": 50,
    "fromY": 39,
    "toX": 53,
    "toY": 40,
    "price": "0"
  },
  {
    "blockNumber": 3275668,
    "ID": "26",
    "fromX": 50,
    "fromY": 35,
    "toX": 53,
    "toY": 38,
    "price": "0"
  },
  {
    "blockNumber": 3275722,
    "ID": "27",
    "fromX": 50,
    "fromY": 32,
    "toX": 53,
    "toY": 34,
    "price": "0"
  },
  {
    "blockNumber": 3767637,
    "ID": "28",
    "fromX": 100,
    "fromY": 1,
    "toX": 100,
    "toY": 1,
    "price": "0"
  },
  {
    "blockNumber": 3906747,
    "ID": "29",
    "fromX": 50,
    "fromY": 46,
    "toX": 53,
    "toY": 47,
    "price": "9000000000000000000"
  },
  {
    "blockNumber": 3989915,
    "ID": "30",
    "fromX": 50,
    "fromY": 46,
    "toX": 53,
    "toY": 47,
    "price": "1000000000000000000"
  },
  {
    "blockNumber": 3989967,
    "ID": "31",
    "fromX": 50,
    "fromY": 32,
    "toX": 53,
    "toY": 32,
    "price": "15000000000000000000"
  },
  {
    "blockNumber": 3989978,
    "ID": "32",
    "fromX": 50,
    "fromY": 33,
    "toX": 53,
    "toY": 33,
    "price": "30000000000000000000"
  },
  {
    "blockNumber": 3989978,
    "ID": "33",
    "fromX": 50,
    "fromY": 34,
    "toX": 53,
    "toY": 34,
    "price": "45000000000000000000"
  },
  {
    "blockNumber": 3989978,
    "ID": "34",
    "fromX": 50,
    "fromY": 35,
    "toX": 53,
    "toY": 35,
    "price": "60000000000000000000"
  },
  {
    "blockNumber": 3989978,
    "ID": "35",
    "fromX": 50,
    "fromY": 36,
    "toX": 53,
    "toY": 36,
    "price": "75000000000000000000"
  },
  {
    "blockNumber": 3989987,
    "ID": "36",
    "fromX": 50,
    "fromY": 37,
    "toX": 53,
    "toY": 37,
    "price": "90000000000000000000"
  },
  {
    "blockNumber": 3989987,
    "ID": "37",
    "fromX": 50,
    "fromY": 37,
    "toX": 53,
    "toY": 37,
    "price": "90000000000000000000"
  },
  {
    "blockNumber": 3989995,
    "ID": "38",
    "fromX": 50,
    "fromY": 38,
    "toX": 53,
    "toY": 38,
    "price": "115000000000000000000"
  },
  {
    "blockNumber": 3989995,
    "ID": "39",
    "fromX": 50,
    "fromY": 39,
    "toX": 53,
    "toY": 39,
    "price": "30000000000000000000"
  },
  {
    "blockNumber": 3989995,
    "ID": "40",
    "fromX": 50,
    "fromY": 40,
    "toX": 53,
    "toY": 40,
    "price": "60000000000000000000"
  },
  {
    "blockNumber": 3989995,
    "ID": "41",
    "fromX": 50,
    "fromY": 41,
    "toX": 53,
    "toY": 41,
    "price": "90000000000000000000"
  },
  {
    "blockNumber": 3990003,
    "ID": "42",
    "fromX": 50,
    "fromY": 42,
    "toX": 50,
    "toY": 42,
    "price": "120000000000000000000"
  },
  {
    "blockNumber": 3990003,
    "ID": "43",
    "fromX": 52,
    "fromY": 42,
    "toX": 53,
    "toY": 42,
    "price": "120000000000000000000"
  },
  {
    "blockNumber": 3990008,
    "ID": "44",
    "fromX": 51,
    "fromY": 42,
    "toX": 51,
    "toY": 42,
    "price": "490000000000000000000"
  },
  {
    "blockNumber": 3990008,
    "ID": "45",
    "fromX": 52,
    "fromY": 48,
    "toX": 52,
    "toY": 48,
    "price": "500000000000000000000"
  },
  {
    "blockNumber": 3990008,
    "ID": "46",
    "fromX": 50,
    "fromY": 43,
    "toX": 53,
    "toY": 43,
    "price": "150000000000000000000"
  },
  {
    "blockNumber": 3990008,
    "ID": "47",
    "fromX": 50,
    "fromY": 44,
    "toX": 53,
    "toY": 44,
    "price": "180000000000000000000"
  },
  {
    "blockNumber": 3990008,
    "ID": "48",
    "fromX": 50,
    "fromY": 45,
    "toX": 53,
    "toY": 45,
    "price": "210000000000000000000"
  },
  {
    "blockNumber": 4315034,
    "ID": "49",
    "fromX": 50,
    "fromY": 32,
    "toX": 53,
    "toY": 38,
    "price": "210000000000000000000"
  },
  {
    "blockNumber": 4315073,
    "ID": "50",
    "fromX": 50,
    "fromY": 46,
    "toX": 53,
    "toY": 47,
    "price": "1000000000000000000000"
  },
  {
    "blockNumber": 4315080,
    "ID": "51",
    "fromX": 50,
    "fromY": 45,
    "toX": 53,
    "toY": 39,
    "price": "500000000000000000000"
  },
  {
    "blockNumber": 4315564,
    "ID": "52",
    "fromX": 51,
    "fromY": 42,
    "toX": 51,
    "toY": 42,
    "price": "10"
  },
  {
    "blockNumber": 4315567,
    "ID": "53",
    "fromX": 51,
    "fromY": 42,
    "toX": 51,
    "toY": 42,
    "price": "0"
  },
  {
    "blockNumber": 13118664,
    "ID": "54",
    "fromX": 77,
    "fromY": 71,
    "toX": 74,
    "toY": 73,
    "price": "1"
  },
  {
    "blockNumber": 13118718,
    "ID": "55",
    "fromX": 88,
    "fromY": 81,
    "toX": 84,
    "toY": 83,
    "price": "1000000000000000"
  },
  {
    "blockNumber": 13118736,
    "ID": "56",
    "fromX": 88,
    "fromY": 81,
    "toX": 84,
    "toY": 83,
    "price": "0"
  },
  {
    "blockNumber": 13118864,
    "ID": "57",
    "fromX": 78,
    "fromY": 71,
    "toX": 74,
    "toY": 73,
    "price": "0"
  },
  {
    "blockNumber": 13118915,
    "ID": "58",
    "fromX": 47,
    "fromY": 59,
    "toX": 1,
    "toY": 26,
    "price": "0"
  },
  {
    "blockNumber": 13118946,
    "ID": "59",
    "fromX": 100,
    "fromY": 47,
    "toX": 1,
    "toY": 64,
    "price": "0"
  },
  {
    "blockNumber": 13118948,
    "ID": "60",
    "fromX": 49,
    "fromY": 41,
    "toX": 44,
    "toY": 43,
    "price": "1000000000000000"
  },
  {
    "blockNumber": 13118957,
    "ID": "61",
    "fromX": 49,
    "fromY": 41,
    "toX": 44,
    "toY": 43,
    "price": "0"
  },
  {
    "blockNumber": 13118978,
    "ID": "62",
    "fromX": 39,
    "fromY": 31,
    "toX": 34,
    "toY": 33,
    "price": "0"
  },
  {
    "blockNumber": 13118979,
    "ID": "63",
    "fromX": 42,
    "fromY": 96,
    "toX": 1,
    "toY": 67,
    "price": "0"
  },
  {
    "blockNumber": 13118987,
    "ID": "64",
    "fromX": 19,
    "fromY": 11,
    "toX": 14,
    "toY": 13,
    "price": "0"
  },
  {
    "blockNumber": 13118992,
    "ID": "65",
    "fromX": 82,
    "fromY": 23,
    "toX": 50,
    "toY": 5,
    "price": "0"
  },
  {
    "blockNumber": 13119000,
    "ID": "66",
    "fromX": 100,
    "fromY": 100,
    "toX": 53,
    "toY": 82,
    "price": "0"
  },
  {
    "blockNumber": 13119023,
    "ID": "67",
    "fromX": 94,
    "fromY": 10,
    "toX": 90,
    "toY": 6,
    "price": "0"
  },
  {
    "blockNumber": 13119050,
    "ID": "68",
    "fromX": 41,
    "fromY": 22,
    "toX": 16,
    "toY": 6,
    "price": "0"
  },
  {
    "blockNumber": 13119126,
    "ID": "69",
    "fromX": 100,
    "fromY": 47,
    "toX": 1,
    "toY": 64,
    "price": "1000000000000000"
  },
  {
    "blockNumber": 13119206,
    "ID": "70",
    "fromX": 88,
    "fromY": 10,
    "toX": 84,
    "toY": 8,
    "price": "0"
  },
  {
    "blockNumber": 13119609,
    "ID": "71",
    "fromX": 7,
    "fromY": 7,
    "toX": 6,
    "toY": 6,
    "price": "0"
  },
  {
    "blockNumber": 13120482,
    "ID": "72",
    "fromX": 89,
    "fromY": 81,
    "toX": 84,
    "toY": 83,
    "price": "0"
  },
  {
    "blockNumber": 13120489,
    "ID": "73",
    "fromX": 89,
    "fromY": 81,
    "toX": 84,
    "toY": 83,
    "price": "2000000000000000000"
  },
  {
    "blockNumber": 13121410,
    "ID": "74",
    "fromX": 19,
    "fromY": 11,
    "toX": 14,
    "toY": 13,
    "price": "50000000000000000000"
  },
  {
    "blockNumber": 13128993,
    "ID": "75",
    "fromX": 79,
    "fromY": 71,
    "toX": 74,
    "toY": 73,
    "price": "0"
  },
  {
    "blockNumber": 13129008,
    "ID": "76",
    "fromX": 79,
    "fromY": 71,
    "toX": 74,
    "toY": 73,
    "price": "100000000000000000000"
  },
  {
    "blockNumber": 13129854,
    "ID": "77",
    "fromX": 100,
    "fromY": 10,
    "toX": 1,
    "toY": 1,
    "price": "0"
  },
  {
    "blockNumber": 13131344,
    "ID": "78",
    "fromX": 62,
    "fromY": 32,
    "toX": 60,
    "toY": 30,
    "price": "0"
  },
  {
    "blockNumber": 13131352,
    "ID": "79",
    "fromX": 75,
    "fromY": 75,
    "toX": 70,
    "toY": 70,
    "price": "0"
  },
  {
    "blockNumber": 13131359,
    "ID": "80",
    "fromX": 75,
    "fromY": 75,
    "toX": 70,
    "toY": 70,
    "price": "5000000000000000000"
  },
  {
    "blockNumber": 13131362,
    "ID": "81",
    "fromX": 90,
    "fromY": 90,
    "toX": 80,
    "toY": 80,
    "price": "0"
  },
  {
    "blockNumber": 13131372,
    "ID": "82",
    "fromX": 90,
    "fromY": 90,
    "toX": 80,
    "toY": 80,
    "price": "5000000000000000000"
  },
  {
    "blockNumber": 13131372,
    "ID": "83",
    "fromX": 62,
    "fromY": 32,
    "toX": 60,
    "toY": 30,
    "price": "5000000000000000000"
  },
  {
    "blockNumber": 13131527,
    "ID": "84",
    "fromX": 45,
    "fromY": 45,
    "toX": 40,
    "toY": 40,
    "price": "0"
  },
  {
    "blockNumber": 13132117,
    "ID": "85",
    "fromX": 100,
    "fromY": 10,
    "toX": 1,
    "toY": 1,
    "price": "100000000000000000000"
  },
  {
    "blockNumber": 13132127,
    "ID": "86",
    "fromX": 100,
    "fromY": 10,
    "toX": 1,
    "toY": 1,
    "price": "0"
  },
  {
    "blockNumber": 13132200,
    "ID": "87",
    "fromX": 75,
    "fromY": 5,
    "toX": 70,
    "toY": 1,
    "price": "0"
  }
]